cribbage/__init__.py
cribbage/card.py
cribbage/game.py
cribbage/main.py
cribbage/players.py
cribbage/score.py
cribbage-1.3.2.dist-info/LICENSE.txt
cribbage-1.3.2.dist-info/WHEEL
cribbage-1.3.2.dist-info/METADATA
cribbage-1.3.2.dist-info/RECORD
