Metadata-Version: 2.1
Name: cribbage
Version: 1.3.2
Summary: Cribbage for your command line
Author: Alex Carlin
Author-email: alex@inkisbetter.com
Requires-Python: >=3.9,<4.0
Classifier: Programming Language :: Python :: 3
Classifier: Programming Language :: Python :: 3.9
Requires-Dist: numpy (>=1.19.4,<2.0.0)
Requires-Dist: pytest (>=6.1.2,<7.0.0)
Requires-Dist: tqdm (>=4.53.0,<5.0.0)
